MANIFEST.in
README.md
requirements.txt
setup.py
api_mocker_generator/__init__.py
api_mocker_generator/__main__.py
api_mocker_generator/api_mocker_generator.py
api_mocker_generator/data_model.py
api_mocker_generator/json_generator.py
api_mocker_generator/logger.py
api_mocker_generator/orchestra.py
api_mocker_generator/output_generator.py
api_mocker_generator/schema_generator.py
api_mocker_generator/swagger_doc.py
api_mocker_generator/template_renderer.py
api_mocker_generator.egg-info/PKG-INFO
api_mocker_generator.egg-info/SOURCES.txt
api_mocker_generator.egg-info/dependency_links.txt
api_mocker_generator.egg-info/entry_points.txt
api_mocker_generator.egg-info/requires.txt
api_mocker_generator.egg-info/top_level.txt
api_mocker_generator/templates/config.json.j2