Metadata-Version: 1.1
Name: api-mocker-generator
Version: 0.0.5
Summary: Generates config and test data for API Mocker node module using Swagger/OpenAPI Spec.
Home-page: https://github.com/namuan/api-mocker-generator
Author: Nauman Leghari
Author-email: nauman@docker-files.com
License: MIT
Keywords: swagger,apis,testing,mock,server
Platform: UNKNOWN
Classifier: Intended Audience :: Developers
Classifier: Natural Language :: English
Classifier: License :: OSI Approved :: MIT License
Classifier: Programming Language :: Python
Classifier: Programming Language :: Python :: 3
Classifier: Programming Language :: Python :: 3.6
